pyearthtools/utils/__init__.py
pyearthtools/utils/config.py
pyearthtools/utils/context.py
pyearthtools/utils/decorators.py
pyearthtools/utils/exceptions.py
pyearthtools/utils/iPython.py
pyearthtools/utils/logger.py
pyearthtools/utils/logger.yaml
pyearthtools/utils/parameter.py
pyearthtools/utils/pyearthtools.yaml
pyearthtools/utils/warnings.py
pyearthtools/utils/data/__init__.py
pyearthtools/utils/data/converter.py
pyearthtools/utils/data/tesselator/__init__.py
pyearthtools/utils/data/tesselator/_patching/__init__.py
pyearthtools/utils/data/tesselator/_patching/_reorder.py
pyearthtools/utils/data/tesselator/_patching/patches.py
pyearthtools/utils/data/tesselator/_patching/subset.py
pyearthtools/utils/initialisation/__init__.py
pyearthtools/utils/initialisation/imports.py
pyearthtools/utils/initialisation/init_parsing.py
pyearthtools/utils/initialisation/load.py
pyearthtools/utils/initialisation/mixin.py
pyearthtools/utils/initialisation/yaml.py
pyearthtools/utils/parsing/__init__.py
pyearthtools/utils/parsing/names.py
pyearthtools/utils/repr_utils/__init__.py
pyearthtools/utils/repr_utils/html.py
pyearthtools/utils/repr_utils/standard.py
pyearthtools/utils/repr_utils/static/__init__.py
pyearthtools/utils/repr_utils/static/css/__init__.py
pyearthtools/utils/repr_utils/static/css/style.css
pyearthtools/utils/repr_utils/static/html/__init__.py
pyearthtools/utils/repr_utils/static/html/icons-svg-inline.html
pyearthtools_utils-0.5.1.dist-info/METADATA
pyearthtools_utils-0.5.1.dist-info/WHEEL
pyearthtools_utils-0.5.1.dist-info/licenses/LICENSE
pyearthtools_utils-0.5.1.dist-info/licenses/NOTICE.md
pyearthtools_utils-0.5.1.dist-info/RECORD
