Metadata-Version: 2.4
Name: pyearthtools-utils
Version: 0.5.1
Dynamic: Description
Dynamic: Description-Content-Type
Summary: Utilities for pyearthtools
Project-URL: homepage, https://pyearthtools.readthedocs.io/
Project-URL: documentation, https://pyearthtools.readthedocs.io/
Project-URL: repository, https://github.com/ACCESS-Community-Hub/PyEarthTools
Maintainer-email: Tennessee Leeuwenburg <tennessee.leeuwenburg@bom.gov.au>
License-File: LICENSE
License-File: NOTICE.md
Keywords: pyearthtools
Classifier: License :: OSI Approved :: Apache Software License
Classifier: Operating System :: OS Independent
Classifier: Programming Language :: Python :: 3
Requires-Python: >=3.11
Requires-Dist: ipython
Requires-Dist: numpy
Requires-Dist: pillow
Requires-Dist: pyyaml
Requires-Dist: scikit-learn
Requires-Dist: tqdm
Requires-Dist: xarray
